[
  {
    "id": 1,
    "name": "ビーバー隊",
    "short": "BVS",
    "graduation": [{ "name": "ビーバー" }, { "name": "ビッグビーバー" }],
    "events": []
  },
  {
    "id": 2,
    "name": "カブ隊",
    "short": "CS",
    "graduation": [{ "name": "うさぎ" }, { "name": "しか" }, { "name": "くま" }]
  },
  {
    "id": 3,
    "name": "ボーイ隊",
    "short": "BS",
    "graduation": [
      { "name": "初級章" },
      { "name": "二級章" },
      { "name": "一級章" },
      { "name": "菊章" }
    ]
  },
  {
    "id": 4,
    "name": "ベンチャー隊",
    "short": "VS",
    "graduation": [
      { "name": "ベンチャー章" },
      { "name": "隼章" },
      { "name": "富士章" }
    ]
  },
  {
    "id": 5,
    "name": "ローバー隊",
    "short": "RS",
    "graduation": []
  }
]
